balathon/__init__.py
balathon/main.py
balathon/codes/1.txt
balathon/codes/2.txt
balathon/codes/3.txt
balathon/codes/4.txt
balathon/codes/5.txt
balathon/codes/6.txt
balathon/codes/7.txt
balathon/codes/8.txt
balathon-0.0.4.dist-info/METADATA
balathon-0.0.4.dist-info/WHEEL
balathon-0.0.4.dist-info/top_level.txt
balathon-0.0.4.dist-info/RECORD
