Metadata-Version: 2.4
Name: balathon
Version: 0.0.4
Summary: A Python package that retrieves code snippets by number
Author: Balathon
License: MIT
